maxnetlib/__init__.py
maxnetlib/core.py
maxnetlib-0.1.0.dist-info/METADATA
maxnetlib-0.1.0.dist-info/WHEEL
maxnetlib-0.1.0.dist-info/top_level.txt
maxnetlib-0.1.0.dist-info/RECORD
