Metadata-Version: 2.4
Name: maxnetlib
Version: 0.1.0
Summary: A simple Python library to implement MaxNet neural network for finding the winning neuron
Home-page: https://github.com/dandan-077/maxnetlib
Author: Daniel Tayade
Author-email: danieltayade2004@gmail.com
Classifier: Programming Language :: Python :: 3
Classifier: License :: OSI Approved :: MIT License
Classifier: Operating System :: OS Independent
Classifier: Intended Audience :: Education
Classifier: Topic :: Scientific/Engineering :: Artificial Intelligence
Requires-Python: >=3.7
Requires-Dist: numpy>=1.18.0
Dynamic: author
Dynamic: author-email
Dynamic: classifier
Dynamic: description-content-type
Dynamic: home-page
Dynamic: requires-dist
Dynamic: requires-python
Dynamic: summary
